{
  "id": "020",
  "type": "default",
  "title": "020",
  "style": "fullwidth",
  "isStartNode": false,
  "backgroundImage": "bg-dungeon.jpg",
  "backgroundColor": "#efefef",
  "paddingTop": "60%",
  "accentColor": "#766278",
  "boxBackgroundColor": "#000000",
  "choiceEnabledGradientStartColor": "#6c5839",
  "choiceEnabledGradientEndColor": "#382c12",
  "choiceDisabledGradientStartColor": "#cda86d",
  "choiceDisabledGradientEndColor": "#9a7931",
  "choiceTextColor": "#dedede",
  "text": {
    "de": "020_de.txt"
  },
  "editorColor": "#10e65c",
  "x": 574,
  "y": 979
}